custosauthenticator/__init__.py
custosauthenticator/custos.py
custos_jupyterhub_authenticator-1.0.5.dist-info/LICENSE
custos_jupyterhub_authenticator-1.0.5.dist-info/METADATA
custos_jupyterhub_authenticator-1.0.5.dist-info/WHEEL
custos_jupyterhub_authenticator-1.0.5.dist-info/top_level.txt
custos_jupyterhub_authenticator-1.0.5.dist-info/RECORD
