Metadata-Version: 2.1
Name: custos-jupyterhub-authenticator
Version: 1.0.5
Summary: Apache Custos Jupyterhub  Authenticator
Home-page: https://github.com/apache/airavata-custos/tree/develop/custos-client-sdks/custos_jupyterhub_authenticator
Author: Custos Developers
Author-email: dev@airavata.apache.org
License: Apache License 2.0
Platform: UNKNOWN
License-File: LICENSE
Requires-Dist: oauthenticator (>=14.2.0)
